Workbook

Sheet 01_Cover
A1: Smartcoop Financial Model v2.0
A3: Company | B3: Smartcoop
A4: Model Type | B4: Driver-Based Financial Model
A5: Purpose | B5: Seed Round / Board Dashboard / Due Diligence
A6: Currency | B6: IDR
A7: Units | B7: Full Rupiah unless stated otherwise
A8: Version | B8: v2.0
A9: Prepared for | B9: Internal / Investor Review
A10: Last Updated | B10: 2026-07-06
A11: Note | B11: Blue cells are hardcoded inputs; black/green cells are formulas or linked outputs.

Sheet 02_Assumptions
A1: 02. Assumptions / Control Panel
A3: Metric / Driver | B3: 2025 | C3: 2026 | D3: 2027 | E3: 2028 | F3: 2029
A5: Customer Growth
A6: Beginning Active Cooperatives | B6: 215 | C6: ='03_Customer_Growth'!B8 -> 246 | D6: ='03_Customer_Growth'!C8 -> 276 | E6: ='03_Customer_Growth'!D8 -> 520 | F6: ='03_Customer_Growth'!E8 -> 912
A7: New Cooperatives Acquired | B7: 35 | C7: 35 | D7: 250 | E7: 400 | F7: 500
A8: Monthly Churn Rate | B8: 0.02 | C8: 0.02 | D8: 0.02 | E8: 0.015 | F8: 0.01
A9: Average Members / Cooperative | B9: 711 | C9: 700 | D9: 410 | E9: 480 | F9: 536
A10: Subscription-Paying % | B10: 1 | C10: 1 | D10: 1 | E10: 1 | F10: 1
A12: Pricing & Revenue Drivers
A13: Setup Fee / Paid Implementation Coop | B13: 40000000 | C13: 40000000 | D13: 40000000 | E13: 40000000 | F13: 40000000
A14: Paid Implementation Coops | B14: 25 | C14: 30 | D14: 130 | E14: 180 | F14: 260
A15: Monthly Subscription Fee | B15: 500000 | C15: 500000 | D15: 500000 | E15: 500000 | F15: 500000
A16: iOS Add-on Monthly Fee | B16: 200000 | C16: 200000 | D16: 200000 | E16: 200000 | F16: 200000
A17: iOS Adoption % | B17: 0.4 | C17: 0.4 | D17: 0.4 | E17: 0.4 | F17: 0.4
A18: White Label Projects | B18: 3 | C18: 4 | D18: 8 | E18: 15 | F18: 25
A19: White Label Fee / Project | B19: 20000000 | C19: 20000000 | D19: 20000000 | E19: 20000000 | F19: 20000000
A20: PPOB Active Cooperatives % | B20: 0.6 | C20: 0.6 | D20: 0.6 | E20: 0.65 | F20: 0.7
A21: PPOB Transactions / Active Coop / Month | B21: 20 | C21: 20 | D21: 20 | E21: 20 | F21: 20
A22: Average PPOB Fee / Transaction | B22: 1000 | C22: 1000 | D22: 1000 | E22: 1000 | F22: 1000
A23: Academy Participants % of Members | B23: 0.001 | C23: 0.001 | D23: 0.001 | E23: 0.001 | F23: 0.001
A24: Academy Average Price / Participant | B24: 200000 | C24: 200000 | D24: 200000 | E24: 200000 | F24: 200000
... A27: Enterprise / Banking / API Revenue | B27: 672000000 | C27: 669000000 | D27: 747000000 | E27: 3660000000 | F27: 10554000000
A29: Cost & Margin Drivers
A30: Cloud Cost / Active Coop / Month | B30: 80000 | C30: 80000 | D30: 70000 | E30: 60000 | F30: 50000
A31: Implementation Cost / Paid Implementation Coop | B31: 6000000 | C31: 6000000 | D31: 5500000 | E31: 5000000 | F31: 4500000
A32: Support Cost / Active Coop / Month | B32: 75000 | C32: 75000 | D32: 70000 | E32: 60000 | F32: 55000
A33: Payment / API Variable Cost % of PPOB Revenue | B33: 0.2 | C33: 0.2 | D33: 0.18 | E33: 0.16 | F33: 0.15
A34: Other Cost of Revenue % | B34: 0.08 | C34: 0.08 | D34: 0.07 | E34: 0.06 | F34: 0.05
A36: Fundraising & Valuation
A37: Seed Investment | B37: 8250000000 | C37: 8250000000 | D37: 8250000000 | E37: 8250000000 | F37: 8250000000
A38: Pre-Money Valuation | B38: 46200000000 | C38: 46200000000 | D38: 46200000000 | E38: 46200000000 | F38: 46200000000
A39: Exit Revenue Multiple - Conservative | B39: 3 | C39: 3 | D39: 3 | E39: 3 | F39: 3
A40: Exit Revenue Multiple - Base Case | B40: 5 | C40: 5 | D40: 5 | E40: 5 | F40: 5
A41: Exit Revenue Multiple - Optimistic | B41: 7 | C41: 7 | D41: 7 | E41: 7 | F41: 7

Sheet 03_Customer_Growth
A1: 03. Customer Growth Model
A3: Metric / Driver | B3: 2025 | C3: 2026 | D3: 2027 | E3: 2028 | F3: 2029
A5: Beginning Active Cooperatives | B5: ='02_Assumptions'!B6 -> 215 | C5: ='02_Assumptions'!C6 -> 246 | D5: ='02_Assumptions'!D6 -> 276 | E5: ='02_Assumptions'!E6 -> 520 | F5: ='02_Assumptions'!F6 -> 912
A6: New Cooperatives Acquired | B6: ='02_Assumptions'!B7 -> 35 | C6: ='02_Assumptions'!C7 -> 35 | D6: ='02_Assumptions'!D7 -> 250 | E6: ='02_Assumptions'!E7 -> 400 | F6: ='02_Assumptions'!F7 -> 500
A7: Churned Cooperatives | B7: =ROUND(B5*'02_Assumptions'!B8,0) -> 4 | C7: =ROUND(C5*'02_Assumptions'!C8,0) -> 5 | D7: =ROUND(D5*'02_Assumptions'!D8,0) -> 6 | E7: =ROUND(E5*'02_Assumptions'!E8,0) -> 8 | F7: =ROUND(F5*'02_Assumptions'!F8,0) -> 9
A8: Ending Active Cooperatives | B8: =B5+B6-B7 -> 246 | C8: =C5+C6-C7 -> 276 | D8: =D5+D6-D7 -> 520 | E8: =E5+E6-E7 -> 912 | F8: =F5+F6-F7 -> 1403
A9: Average Members / Cooperative | B9: ='02_Assumptions'!B9 -> 711 | C9: ='02_Assumptions'!C9 -> 700 | D9: ='02_Assumptions'!D9 -> 410 | E9: ='02_Assumptions'!E9 -> 480 | F9: ='02_Assumptions'!F9 -> 536
A10: Total Cooperative Members | B10: =B8*B9 -> 174906 | C10: =C8*C9 -> 193200 | D10: =D8*D9 -> 213200 | E10: =E8*E9 -> 437760 | F10: =F8*F9 -> 752008
A11: YoY Active Coop Growth | B11: - | C11: =IF(B8=0,0,C8/B8-1) -> 0.12195122 | D11: =IF(C8=0,0,D8/C8-1) -> 0.88405797 | E11: =IF(D8=0,0,E8/D8-1) -> 0.75384615 | F11: =IF(E8=0,0,F8/E8-1) -> 0.53837719

Sheet 04_Revenue_Engine
A1: 04. Revenue Engine
A3: Metric / Driver | B3: 2025 | C3: 2026 | D3: 2027 | E3: 2028 | F3: 2029
A5: Setup / Implementation Revenue | B5: ='02_Assumptions'!B14*'02_Assumptions'!B13 -> 1000000000 | C5: ='02_Assumptions'!C14*'02_Assumptions'!C13 -> 1200000000 | D5: ='02_Assumptions'!D14*'02_Assumptions'!D13 -> 5200000000 | E5: ='02_Assumptions'!E14*'02_Assumptions'!E13 -> 7200000000 | F5: ='02_Assumptions'!F14*'02_Assumptions'!F13 -> 10400000000
A6: SaaS Subscription Revenue | B6: ='03_Customer_Growth'!B8*'02_Assumptions'!B10*'02_Assumptions'!B15*12 -> 1476000000 | C6: ='03_Customer_Growth'!C8*'02_Assumptions'!C10*'02_Assumptions'!C15*12 -> 1656000000 | D6: ='03_Customer_Growth'!D8*'02_Assumptions'!D10*'02_Assumptions'!D15*12 -> 3120000000 | E6: ='03_Customer_Growth'!E8*'02_Assumptions'!E10*'02_Assumptions'!E15*12 -> 5472000000 | F6: ='03_Customer_Growth'!F8*'02_Assumptions'!F10*'02_Assumptions'!F15*12 -> 8418000000
A7: iOS Add-on Revenue | B7: ='03_Customer_Growth'!B8*'02_Assumptions'!B17*'02_Assumptions'!B16*12 -> 236160000 | C7: ='03_Customer_Growth'!C8*'02_Assumptions'!C17*'02_Assumptions'!C16*12 -> 264960000 | D7: ='03_Customer_Growth'!D8*'02_Assumptions'!D17*'02_Assumptions'!D16*12 -> 499200000 | E7: ='03_Customer_Growth'!E8*'02_Assumptions'!E17*'02_Assumptions'!E16*12 -> 875520000 | F7: ='03_Customer_Growth'!F8*'02_Assumptions'!F17*'02_Assumptions'!F16*12 -> 1.34688e+09
A8: White Label Revenue | B8: ='02_Assumptions'!B18*'02_Assumptions'!B19 -> 60000000 | C8: ='02_Assumptions'!C18*'02_Assumptions'!C19 -> 80000000 | D8: ='02_Assumptions'!D18*'02_Assumptions'!D19 -> 160000000 | E8: ='02_Assumptions'!E18*'02_Assumptions'!E19 -> 300000000 | F8: ='02_Assumptions'!F18*'02_Assumptions'!F19 -> 500000000
A9: PPOB Transaction Revenue | B9: ='03_Customer_Growth'!B8*'02_Assumptions'!B20*'02_Assumptions'!B21*12*'02_Assumptions'!B22 -> 35424000 | C9: ='03_Customer_Growth'!C8*'02_Assumptions'!C20*'02_Assumptions'!C21*12*'02_Assumptions'!C22 -> 39744000 | D9: ='03_Customer_Growth'!D8*'02_Assumptions'!D20*'02_Assumptions'!D21*12*'02_Assumptions'!D22 -> 74880000 | E9: ='03_Customer_Growth'!E8*'02_Assumptions'!E20*'02_Assumptions'!E21*12*'02_Assumptions'!E22 -> 1.42272e+08 | F9: ='03_Customer_Growth'!F8*'02_Assumptions'!F20*'02_Assumptions'!F21*12*'02_Assumptions'!F22 -> 235704000
A10: Smartcoop Academy Revenue | B10: ='03_Customer_Growth'!B10*'02_Assumptions'!B23*'02_Assumptions'!B24 -> 34981200 | C10: ='03_Customer_Growth'!C10*'02_Assumptions'!C23*'02_Assumptions'!C24 -> 38640000 | D10: ='03_Customer_Growth'!D10*'02_Assumptions'!D23*'02_Assumptions'!D24 -> 42640000 | E10: ='03_Customer_Growth'!E10*'02_Assumptions'!E23*'02_Assumptions'!E24 -> 87552000 | F10: ='03_Customer_Growth'!F10*'02_Assumptions'!F23*'02_Assumptions'!F24 -> 150401600
A11: Offline Training Revenue | B11: ='02_Assumptions'!B25*12*'02_Assumptions'!B26 -> 210000000 | C11: ='02_Assumptions'!C25*12*'02_Assumptions'!C26 -> 240000000 | D11: ='02_Assumptions'!D25*12*'02_Assumptions'!D26 -> 300000000 | E11: ='02_Assumptions'!E25*12*'02_Assumptions'!E26 -> 360000000 | F11: ='02_Assumptions'!F25*12*'02_Assumptions'!F26 -> 450000000
A12: Enterprise / Banking / API Revenue | B12: ='02_Assumptions'!B27 -> 672000000 | C12: ='02_Assumptions'!C27 -> 669000000 | D12: ='02_Assumptions'!D27 -> 747000000 | E12: ='02_Assumptions'!E27 -> 3660000000 | F12: ='02_Assumptions'!F27 -> 10554000000
A13: Total Revenue | B13: =SUM(B5:B12) -> 3724565200 | C13: =SUM(C5:C12) -> 4188344000 | D13: =SUM(D5:D12) -> 10143720000 | E13: =SUM(E5:E12) -> 18097344000 | F13: =SUM(F5:F12) -> 32054985600
A14: ARR / Recurring SaaS Run-Rate | B14: =B6+B7 -> 1712160000 | C14: =C6+C7 -> 1920960000 | D14: =D6+D7 -> 3619200000 | E14: =E6+E7 -> 6347520000 | F14: =F6+F7 -> 9764880000
A15: ARPU / Active Coop | B15: =IF('03_Customer_Growth'!B8=0,0,B13/'03_Customer_Growth'!B8) -> 15140509 | C15: =IF('03_Customer_Growth'!C8=0,0,C13/'03_Customer_Growth'!C8) -> 15175159 | D15: =IF('03_Customer_Growth'!D8=0,0,D13/'03_Customer_Growth'!D8) -> 19507154 | E15: =IF('03_Customer_Growth'!E8=0,0,E13/'03_Customer_Growth'!E8) -> 19843579 | F15: =IF('03_Customer_Growth'!F8=0,0,F13/'03_Customer_Growth'!F8) -> 22847459

Sheet 05_COGS
A1: 05. Cost of Revenue (COGS)
A3: Metric / Driver | B3: 2025 | C3: 2026 | D3: 2027 | E3: 2028 | F3: 2029
A5: Cloud Infrastructure | B5: ='03_Customer_Growth'!B8*'02_Assumptions'!B30*12 -> 236160000 | C5: ='03_Customer_Growth'!C8*'02_Assumptions'!C30*12 -> 264960000 | D5: ='03_Customer_Growth'!D8*'02_Assumptions'!D30*12 -> 436800000 | E5: ='03_Customer_Growth'!E8*'02_Assumptions'!E30*12 -> 656640000 | F5: ='03_Customer_Growth'!F8*'02_Assumptions'!F30*12 -> 841800000
A6: Implementation / Onboarding Cost | B6: ='02_Assumptions'!B14*'02_Assumptions'!B31 -> 150000000 | C6: ='02_Assumptions'!C14*'02_Assumptions'!C31 -> 180000000 | D6: ='02_Assumptions'!D14*'02_Assumptions'!D31 -> 715000000 | E6: ='02_Assumptions'!E14*'02_Assumptions'!E31 -> 900000000 | F6: ='02_Assumptions'!F14*'02_Assumptions'!F31 -> 1170000000
A7: Customer Support Cost | B7: ='03_Customer_Growth'!B8*'02_Assumptions'!B32*12 -> 221400000 | C7: ='03_Customer_Growth'!C8*'02_Assumptions'!C32*12 -> 248400000 | D7: ='03_Customer_Growth'!D8*'02_Assumptions'!D32*12 -> 436800000 | E7: ='03_Customer_Growth'!E8*'02_Assumptions'!E32*12 -> 656640000 | F7: ='03_Customer_Growth'!F8*'02_Assumptions'!F32*12 -> 925980000
A8: Payment / API Variable Cost | B8: ='04_Revenue_Engine'!B9*'02_Assumptions'!B33 -> 7084800 | C8: ='04_Revenue_Engine'!C9*'02_Assumptions'!C33 -> 7948800 | D8: ='04_Revenue_Engine'!D9*'02_Assumptions'!D33 -> 13478400 | E8: ='04_Revenue_Engine'!E9*'02_Assumptions'!E33 -> 22763520 | F8: ='04_Revenue_Engine'!F9*'02_Assumptions'!F33 -> 35355600
A9: Other Cost of Revenue | B9: ='04_Revenue_Engine'!B13*'02_Assumptions'!B34 -> 297965216 | C9: ='04_Revenue_Engine'!C13*'02_Assumptions'!C34 -> 335067520 | D9: ='04_Revenue_Engine'!D13*'02_Assumptions'!D34 -> 7.100604e+08 | E9: ='04_Revenue_Engine'!E13*'02_Assumptions'!E34 -> 1085840640 | F9: ='04_Revenue_Engine'!F13*'02_Assumptions'!F34 -> 1602749280
A10: Total COGS | B10: =SUM(B5:B9) -> 912610016 | C10: =SUM(C5:C9) -> 1036376320 | D10: =SUM(D5:D9) -> 2312138800 | E10: =SUM(E5:E9) -> 3321884160 | F10: =SUM(F5:F9) -> 4575884880
A11: Gross Profit | B11: ='04_Revenue_Engine'!B13-B10 -> 2811955184 | C11: ='04_Revenue_Engine'!C13-C10 -> 3151967680 | D11: ='04_Revenue_Engine'!D13-D10 -> 7831581200 | E11: ='04_Revenue_Engine'!E13-E10 -> 14775459840 | F11: ='04_Revenue_Engine'!F13-F10 -> 27479100720
A12: Gross Margin | B12: =IF('04_Revenue_Engine'!B13=0,0,B11/'04_Revenue_Engine'!B13) -> 0.75497542 | C12: =IF('04_Revenue_Engine'!C13=0,0,C11/'04_Revenue_Engine'!C13) -> 0.75255702 | D12: =IF('04_Revenue_Engine'!D13=0,0,D11/'04_Revenue_Engine'!D13) -> 0.77206204 | E12: =IF('04_Revenue_Engine'!E13=0,0,E11/'04_Revenue_Engine'!E13) -> 0.81644355 | F12: =IF('04_Revenue_Engine'!F13=0,0,F11/'04_Revenue_Engine'!F13) -> 0.85724889

Sheet 06_HR_Planning
A1: 06. HR Planning
A3: Metric / Driver | B3: 2025 | C3: 2026 | D3: 2027 | E3: 2028 | F3: 2029
A5: Engineering / Product FTE | B5: 5 | C5: 6 | D5: 8 | E5: 11 | F5: 15
A6: Sales & Partnership FTE | B6: 3 | C6: 4 | D6: 7 | E6: 10 | F6: 14
A7: Marketing FTE | B7: 2 | C7: 3 | D7: 4 | E7: 5 | F7: 7
A8: Customer Success / Support FTE | B8: 4 | C8: 5 | D8: 8 | E8: 12 | F8: 18
A9: Finance / HR / Admin FTE | B9: 2 | C9: 3 | D9: 4 | E9: 5 | F9: 6
A10: Management / Leadership FTE | B10: 3 | C10: 3 | D10: 4 | E10: 4 | F10: 5
A11: Total FTE | B11: =SUM(B5:B10) -> 19 | C11: =SUM(C5:C10) -> 24 | D11: =SUM(D5:D10) -> 35 | E11: =SUM(E5:E10) -> 47 | F11: =SUM(F5:F10) -> 65
A12: Average Salary / Month | B12: 10500000 | C12: 11000000 | D12: 11500000 | E12: 12000000 | F12: 12500000
A13: Total Payroll | B13: =B11*B12*12 -> 2394000000 | C13: =C11*C12*12 -> 3168000000 | D13: =D11*D12*12 -> 4830000000 | E13: =E11*E12*12 -> 6768000000 | F13: =F11*F12*12 -> 9750000000

Sheet 07_OPEX
A1: 07. Operating Expenses
A3: Metric / Driver | B3: 2025 | C3: 2026 | D3: 2027 | E3: 2028 | F3: 2029
A5: Payroll | B5: ='06_HR_Planning'!B13 -> 2394000000 | C5: ='06_HR_Planning'!C13 -> 3168000000 | D5: ='06_HR_Planning'!D13 -> 4830000000 | E5: ='06_HR_Planning'!E13 -> 6768000000 | F5: ='06_HR_Planning'!F13 -> 9750000000
A6: Sales & Marketing Spend | B6: 400000000 | C6: 600000000 | D6: 900000000 | E6: 1500000000 | F6: 2200000000
A7: Office, Utilities & Internet | B7: 180000000 | C7: 220000000 | D7: 300000000 | E7: 400000000 | F7: 550000000
A8: Software Tools & Subscriptions | B8: 120000000 | C8: 150000000 | D8: 220000000 | E8: 350000000 | F8: 500000000
A9: Legal, Accounting & Compliance | B9: 80000000 | C9: 100000000 | D9: 150000000 | E9: 200000000 | F9: 300000000
A10: Travel & Events | B10: 150000000 | C10: 180000000 | D10: 300000000 | E10: 500000000 | F10: 800000000
A11: Recruitment & Training | B11: 70000000 | C11: 90000000 | D11: 150000000 | E11: 250000000 | F11: 350000000
A12: Other G&A | B12: 100000000 | C12: 130000000 | D12: 200000000 | E12: 300000000 | F12: 500000000
A13: Total OPEX | B13: =SUM(B5:B12) -> 3494000000 | C13: =SUM(C5:C12) -> 4638000000 | D13: =SUM(D5:D12) -> 7050000000 | E13: =SUM(E5:E12) -> 10268000000 | F13: =SUM(F5:F12) -> 14950000000

Sheet 08_EBITDA
A1: 08. EBITDA Summary
A3: Metric / Driver | B3: 2025 | C3: 2026 | D3: 2027 | E3: 2028 | F3: 2029
A5: Total Revenue | B5: ='04_Revenue_Engine'!B13 -> 3724565200 | C5: ='04_Revenue_Engine'!C13 -> 4188344000 | D5: ='04_Revenue_Engine'!D13 -> 10143720000 | E5: ='04_Revenue_Engine'!E13 -> 18097344000 | F5: ='04_Revenue_Engine'!F13 -> 32054985600
A6: COGS | B6: ='05_COGS'!B10 -> 912610016 | C6: ='05_COGS'!C10 -> 1036376320 | D6: ='05_COGS'!D10 -> 2312138800 | E6: ='05_COGS'!E10 -> 3321884160 | F6: ='05_COGS'!F10 -> 4575884880
A7: Gross Profit | B7: =B5-B6 -> 2811955184 | C7: =C5-C6 -> 3151967680 | D7: =D5-D6 -> 7831581200 | E7: =E5-E6 -> 14775459840 | F7: =F5-F6 -> 27479100720
A8: Gross Margin | B8: =IF(B5=0,0,B7/B5) -> 0.75497542 | C8: =IF(C5=0,0,C7/C5) -> 0.75255702 | D8: =IF(D5=0,0,D7/D5) -> 0.77206204 | E8: =IF(E5=0,0,E7/E5) -> 0.81644355 | F8: =IF(F5=0,0,F7/F5) -> 0.85724889
A9: OPEX | B9: ='07_OPEX'!B13 -> 3494000000 | C9: ='07_OPEX'!C13 -> 4638000000 | D9: ='07_OPEX'!D13 -> 7050000000 | E9: ='07_OPEX'!E13 -> 10268000000 | F9: ='07_OPEX'!F13 -> 14950000000
A10: EBITDA | B10: =B7-B9 -> -682044816 | C10: =C7-C9 -> -1486032320 | D10: =D7-D9 -> 781581200 | E10: =E7-E9 -> 4507459840 | F10: =F7-F9 -> 12529100720
A11: EBITDA Margin | B11: =IF(B5=0,0,B10/B5) -> -0.18312065 | C11: =IF(C5=0,0,C10/C5) -> -0.35480188 | D11: =IF(D5=0,0,D10/D5) -> 0.077050747 | E11: =IF(E5=0,0,E10/E5) -> 0.24906748 | F11: =IF(F5=0,0,F10/F5) -> 0.39086278

Sheet 09_Cash_Flow
A1: 09. Cash Flow & Runway
A3: Metric / Driver | B3: 2025 | C3: 2026 | D3: 2027 | E3: 2028 | F3: 2029
A5: Opening Cash | B5: 0 | C5: =B8 -> -682044816 | D5: =C8 -> 6081922864 | E5: =D8 -> 6863504064 | F5: =E8 -> 11370963904
A6: Seed Investment Inflow | B6: =IF(B$3=2026,'02_Assumptions'!B37,0) -> 0 | C6: =IF(C$3=2026,'02_Assumptions'!C37,0) -> 8250000000 | D6: =IF(D$3=2026,'02_Assumptions'!D37,0) -> 0 | E6: =IF(E$3=2026,'02_Assumptions'!E37,0) -> 0 | F6: =IF(F$3=2026,'02_Assumptions'!F37,0) -> 0
A7: EBITDA | B7: ='08_EBITDA'!B10 -> -682044816 | C7: ='08_EBITDA'!C10 -> -1486032320 | D7: ='08_EBITDA'!D10 -> 781581200 | E7: ='08_EBITDA'!E10 -> 4507459840 | F7: ='08_EBITDA'!F10 -> 12529100720
A8: Ending Cash | B8: =B5+B6+B7 -> -682044816 | C8: =C5+C6+C7 -> 6081922864 | D8: =D5+D6+D7 -> 6863504064 | E8: =E5+E6+E7 -> 11370963904 | F8: =F5+F6+F7 -> 23900064624
A9: Average Monthly Burn / Profit | B9: =ABS(MIN(B7/12,0)) -> 56837068 | C9: =ABS(MIN(C7/12,0)) -> 1.2383603e+08 | D9: =ABS(MIN(D7/12,0)) -> 0 | E9: =ABS(MIN(E7/12,0)) -> 0 | F9: =ABS(MIN(F7/12,0)) -> 0
A10: Runway (Months) | B10: =IF(B9=0,"Profitable",B8/B9) -> -12 | C10: =IF(C9=0,"Profitable",C8/C9) -> 49.11271 | D10: =IF(D9=0,"Profitable",D8/D9) -> Profitable | E10: =IF(E9=0,"Profitable",E8/E9) -> Profitable | F10: =IF(F9=0,"Profitable",F8/F9) -> Profitable

Sheet 10_SaaS_Metrics
A1: 10. SaaS Metrics
A3: Metric / Driver | B3: 2025 | C3: 2026 | D3: 2027 | E3: 2028 | F3: 2029
A5: MRR | B5: ='04_Revenue_Engine'!B14/12 -> 142680000 | C5: ='04_Revenue_Engine'!C14/12 -> 160080000 | D5: ='04_Revenue_Engine'!D14/12 -> 301600000 | E5: ='04_Revenue_Engine'!E14/12 -> 528960000 | F5: ='04_Revenue_Engine'!F14/12 -> 813740000
A6: ARR | B6: ='04_Revenue_Engine'!B14 -> 1712160000 | C6: ='04_Revenue_Engine'!C14 -> 1920960000 | D6: ='04_Revenue_Engine'!D14 -> 3619200000 | E6: ='04_Revenue_Engine'!E14 -> 6347520000 | F6: ='04_Revenue_Engine'!F14 -> 9764880000
A7: ARPU / Active Coop | B7: ='04_Revenue_Engine'!B15 -> 15140509 | C7: ='04_Revenue_Engine'!C15 -> 15175159 | D7: ='04_Revenue_Engine'!D15 -> 19507154 | E7: ='04_Revenue_Engine'!E15 -> 19843579 | F7: ='04_Revenue_Engine'!F15 -> 22847459
A8: Gross Margin | B8: ='05_COGS'!B12 -> 0.75497542 | C8: ='05_COGS'!C12 -> 0.75255702 | D8: ='05_COGS'!D12 -> 0.77206204 | E8: ='05_COGS'!E12 -> 0.81644355 | F8: ='05_COGS'!F12 -> 0.85724889
A9: Monthly Churn | B9: ='02_Assumptions'!B8 -> 0.02 | C9: ='02_Assumptions'!C8 -> 0.02 | D9: ='02_Assumptions'!D8 -> 0.02 | E9: ='02_Assumptions'!E8 -> 0.015 | F9: ='02_Assumptions'!F8 -> 0.01
A10: Annual Churn | B10: =1-(1-B9)^12 -> 0.21528328 | C10: =1-(1-C9)^12 -> 0.21528328 | D10: =1-(1-D9)^12 -> 0.21528328 | E10: =1-(1-E9)^12 -> 0.16586803 | F10: =1-(1-F9)^12 -> 0.11361513
A11: Estimated CAC / New Coop | B11: =IF('02_Assumptions'!B7=0,0,('07_OPEX'!B6+'07_OPEX'!B5*0.35)/'02_Assumptions'!B7) -> 35368571 | C11: =IF('02_Assumptions'!C7=0,0,('07_OPEX'!C6+'07_OPEX'!C5*0.35)/'02_Assumptions'!C7) -> 48822857 | D11: =IF('02_Assumptions'!D7=0,0,('07_OPEX'!D6+'07_OPEX'!D5*0.35)/'02_Assumptions'!D7) -> 10362000 | E11: =IF('02_Assumptions'!E7=0,0,('07_OPEX'!E6+'07_OPEX'!E5*0.35)/'02_Assumptions'!E7) -> 9672000 | F11: =IF('02_Assumptions'!F7=0,0,('07_OPEX'!F6+'07_OPEX'!F5*0.35)/'02_Assumptions'!F7) -> 11225000
A12: Estimated LTV | B12: =IF(B9=0,0,(B5*B8)/B9) -> 5.3859947e+09 | C12: =IF(C9=0,0,(C5*C8)/C9) -> 6.0234664e+09 | D12: =IF(D9=0,0,(D5*D8)/D9) -> 1.1642696e+10 | E12: =IF(E9=0,0,(E5*E8)/E9) -> 2.8791065e+10 | F12: =IF(F9=0,0,(F5*F8)/F9) -> 6.9757771e+10
A13: LTV / CAC | B13: =IF(B11=0,0,B12/B11) -> 152.28194 | C13: =IF(C11=0,0,C12/C11) -> 123.3739 | D13: =IF(D11=0,0,D12/D11) -> 1123.5954 | E13: =IF(E11=0,0,E12/E11) -> 2976.7437 | F13: =IF(F11=0,0,F12/F11) -> 6214.5007
A14: CAC Payback (Months) | B14: =IF((B5*B8)=0,0,B11/(B5*B8)) -> 0.32833834 | C14: =IF((C5*C8)=0,0,C11/(C5*C8)) -> 0.4052721 | D14: =IF((D5*D8)=0,0,D11/(D5*D8)) -> 0.044500004 | E14: =IF((E5*E8)=0,0,E11/(E5*E8)) -> 0.022395837 | F14: =IF((F5*F8)=0,0,F11/(F5*F8)) -> 0.016091397
A15: Rule of 40 | B15: ='08_EBITDA'!B11 -> -0.18312065 | C15: =(('04_Revenue_Engine'!C13/'04_Revenue_Engine'!B13)-1)+'08_EBITDA'!C11 -> -0.23028297 | D15: =(('04_Revenue_Engine'!D13/'04_Revenue_Engine'!C13)-1)+'08_EBITDA'!D11 -> 1.4989435 | E15: =(('04_Revenue_Engine'!E13/'04_Revenue_Engine'!D13)-1)+'08_EBITDA'!E11 -> 1.0331609 | F15: =(('04_Revenue_Engine'!F13/'04_Revenue_Engine'!E13)-1)+'08_EBITDA'!F11 -> 1.1621164

Sheet 11_Valuation
A1: 11. Valuation
A3: Metric / Driver | B3: 2025 | C3: 2026 | D3: 2027 | E3: 2028 | F3: 2029
A5: Revenue | B5: ='04_Revenue_Engine'!B13 -> 3724565200 | C5: ='04_Revenue_Engine'!C13 -> 4188344000 | D5: ='04_Revenue_Engine'!D13 -> 10143720000 | E5: ='04_Revenue_Engine'!E13 -> 18097344000 | F5: ='04_Revenue_Engine'!F13 -> 32054985600
A6: ARR | B6: ='10_SaaS_Metrics'!B6 -> 1712160000 | C6: ='10_SaaS_Metrics'!C6 -> 1920960000 | D6: ='10_SaaS_Metrics'!D6 -> 3619200000 | E6: ='10_SaaS_Metrics'!E6 -> 6347520000 | F6: ='10_SaaS_Metrics'!F6 -> 9764880000
A7: Revenue Multiple - Conservative | B7: ='02_Assumptions'!B39 -> 3 | C7: ='02_Assumptions'!C39 -> 3 | D7: ='02_Assumptions'!D39 -> 3 | E7: ='02_Assumptions'!E39 -> 3 | F7: ='02_Assumptions'!F39 -> 3
A8: Revenue Multiple - Base | B8: ='02_Assumptions'!B40 -> 5 | C8: ='02_Assumptions'!C40 -> 5 | D8: ='02_Assumptions'!D40 -> 5 | E8: ='02_Assumptions'!E40 -> 5 | F8: ='02_Assumptions'!F40 -> 5
A9: Revenue Multiple - Optimistic | B9: ='02_Assumptions'!B41 -> 7 | C9: ='02_Assumptions'!C41 -> 7 | D9: ='02_Assumptions'!D41 -> 7 | E9: ='02_Assumptions'!E41 -> 7 | F9: ='02_Assumptions'!F41 -> 7
A10: Enterprise Value - Conservative | B10: =B5*B7 -> 11173695600 | C10: =C5*C7 -> 12565032000 | D10: =D5*D7 -> 30431160000 | E10: =E5*E7 -> 54292032000 | F10: =F5*F7 -> 96164956800
A11: Enterprise Value - Base | B11: =B5*B8 -> 18622826000 | C11: =C5*C8 -> 20941720000 | D11: =D5*D8 -> 50718600000 | E11: =E5*E8 -> 90486720000 | F11: =F5*F8 -> 160274928000
A12: Enterprise Value - Optimistic | B12: =B5*B9 -> 26071956400 | C12: =C5*C9 -> 29318408000 | D12: =D5*D9 -> 71006040000 | E12: =E5*E9 -> 126681408000 | F12: =F5*F9 -> 224384899200
A13: Seed Pre-Money Valuation | B13: ='02_Assumptions'!B38 -> 46200000000 | C13: ='02_Assumptions'!C38 -> 46200000000 | D13: ='02_Assumptions'!D38 -> 46200000000 | E13: ='02_Assumptions'!E38 -> 46200000000 | F13: ='02_Assumptions'!F38 -> 46200000000
A14: Seed Post-Money Valuation | B14: =B13+'02_Assumptions'!B37 -> 54450000000 | C14: =C13+'02_Assumptions'!C37 -> 54450000000 | D14: =D13+'02_Assumptions'!D37 -> 54450000000 | E14: =E13+'02_Assumptions'!E37 -> 54450000000 | F14: =F13+'02_Assumptions'!F37 -> 54450000000
A15: Implied Seed Equity % | B15: =IF(B14=0,0,'02_Assumptions'!B37/B14) -> 0.15151515 | C15: =IF(C14=0,0,'02_Assumptions'!C37/C14) -> 0.15151515 | D15: =IF(D14=0,0,'02_Assumptions'!D37/D14) -> 0.15151515 | E15: =IF(E14=0,0,'02_Assumptions'!E37/E14) -> 0.15151515 | F15: =IF(F14=0,0,'02_Assumptions'!F37/F14) -> 0.15151515

Sheet 12_Cap_Table
A1: 12. Cap Table
A3: Shareholder | B3: Pre-Seed / Current | C3: Seed Investment | D3: Post-Seed Ownership | E3: Notes
A4: Founders / Existing Shareholders | B4: 1 | C4: 50 | D4: =B4*(1-D6) -> 0.84848485 | E4: Before employee option pool adjustments
A5: Employee Option Pool (ESOP) | B5: 0.02 | C5: 0 | D5: =B5 -> 0.02 | E5: Optional; input can be adjusted
A6: Seed Investor | B6: 0 | C6: ='02_Assumptions'!B37 -> 8250000000 | D6: =IF('11_Valuation'!B14=0,0,'02_Assumptions'!B37/'11_Valuation'!B14) -> 0.15151515 | E6: Formula uses Seed Investment / Post-Money Valuation
A7: Total | B7: =SUM(B4:B6) -> 1.02 | C7: =SUM(C4:C6) -> 8250000050 | D7: =SUM(D4:D6) -> 1.02

Sheet 13_Investor_Return
A1: 13. Potential Investor Return
A3: Indicator | B3: Conservative | C3: Base Case | D3: Optimistic
A5: Projected Revenue (2029) | B5: ='04_Revenue_Engine'!F13*0.875 -> 28048112400 | C5: ='04_Revenue_Engine'!F13 -> 32054985600 | D5: ='04_Revenue_Engine'!F13*1.1875 -> 38065295400
A6: Revenue Multiple | B6: ='02_Assumptions'!F39 -> 3 | C6: ='02_Assumptions'!F40 -> 5 | D6: ='02_Assumptions'!F41 -> 7
A7: Estimated Exit Valuation | B7: =B5*B6 -> 84144337200 | C7: =C5*C6 -> 160274928000 | D7: =D5*D6 -> 266457067800
A8: Investor Equity % | B8: ='12_Cap_Table'!D6 -> 0.15151515 | C8: ='12_Cap_Table'!D6 -> 0.15151515 | D8: ='12_Cap_Table'!D6 -> 0.15151515
A9: Investor Equity Value | B9: =B7*B8 -> 12749142000 | C9: =C7*C8 -> 24284080000 | D9: =D7*D8 -> 40372283000
A10: Initial Investment | B10: ='02_Assumptions'!B37 -> 8250000000 | C10: ='02_Assumptions'!B37 -> 8250000000 | D10: ='02_Assumptions'!B37 -> 8250000000
A11: MOIC | B11: =IF(B10=0,0,B9/B10) -> 1.5453505 | C11: =IF(C10=0,0,C9/C10) -> 2.9435248 | D11: =IF(D10=0,0,D9/D10) -> 4.8936101
A12: Estimated IRR (5 Years) | B12: =IF(B11=0,0,B11^(1/5)-1) -> 0.090951395 | C12: =IF(C11=0,0,C11^(1/5)-1) -> 0.24100503 | D12: =IF(D11=0,0,D11^(1/5)-1) -> 0.37380747

Sheet 14_Dashboard
A1: 14. Executive Dashboard
A3: Smartcoop Financial Model v2.0 - Key Outputs
A5: 2029 Revenue | B5: ='04_Revenue_Engine'!F13 -> 32054985600 | C5: 2029 ARR | D5: ='10_SaaS_Metrics'!F6 -> 9764880000 | E5: 2029 EBITDA | F5: ='08_EBITDA'!F10 -> 12529100720 | G5: 2029 Active Coops | H5: ='03_Customer_Growth'!F8 -> 1403
A8: Seed Equity % | B8: ='11_Valuation'!B15 -> 0.15151515 | C8: Base Exit Valuation | D8: ='13_Investor_Return'!C7 -> 160274928000 | E8: Base MOIC | F8: ='13_Investor_Return'!C11 -> 2.9435248 | G8: Base IRR | H8: ='13_Investor_Return'!C12 -> 0.24100503
A11: Metric / Driver | B11: 2025 | C11: 2026 | D11: 2027 | E11: 2028 | F11: 2029
A12: Active Cooperatives | B12: ='03_Customer_Growth'!B8 -> 246 | C12: ='03_Customer_Growth'!C8 -> 276 | D12: ='03_Customer_Growth'!D8 -> 520 | E12: ='03_Customer_Growth'!E8 -> 912 | F12: ='03_Customer_Growth'!F8 -> 1403
A13: Members | B13: ='03_Customer_Growth'!B10 -> 174906 | C13: ='03_Customer_Growth'!C10 -> 193200 | D13: ='03_Customer_Growth'!D10 -> 213200 | E13: ='03_Customer_Growth'!E10 -> 437760 | F13: ='03_Customer_Growth'!F10 -> 752008
A14: Revenue | B14: ='04_Revenue_Engine'!B13 -> 3724565200 | C14: ='04_Revenue_Engine'!C13 -> 4188344000 | D14: ='04_Revenue_Engine'!D13 -> 10143720000 | E14: ='04_Revenue_Engine'!E13 -> 18097344000 | F14: ='04_Revenue_Engine'!F13 -> 32054985600
A15: ARR | B15: ='10_SaaS_Metrics'!B6 -> 1712160000 | C15: ='10_SaaS_Metrics'!C6 -> 1920960000 | D15: ='10_SaaS_Metrics'!D6 -> 3619200000 | E15: ='10_SaaS_Metrics'!E6 -> 6347520000 | F15: ='10_SaaS_Metrics'!F6 -> 9764880000
A16: Gross Margin | B16: ='05_COGS'!B12 -> 0.75497542 | C16: ='05_COGS'!C12 -> 0.75255702 | D16: ='05_COGS'!D12 -> 0.77206204 | E16: ='05_COGS'!E12 -> 0.81644355 | F16: ='05_COGS'!F12 -> 0.85724889
A17: EBITDA | B17: ='08_EBITDA'!B10 -> -682044816 | C17: ='08_EBITDA'!C10 -> -1486032320 | D17: ='08_EBITDA'!D10 -> 781581200 | E17: ='08_EBITDA'!E10 -> 4507459840 | F17: ='08_EBITDA'!F10 -> 12529100720
A18: EBITDA Margin | B18: ='08_EBITDA'!B11 -> -0.18312065 | C18: ='08_EBITDA'!C11 -> -0.35480188 | D18: ='08_EBITDA'!D11 -> 0.077050747 | E18: ='08_EBITDA'!E11 -> 0.24906748 | F18: ='08_EBITDA'!F11 -> 0.39086278
A19: Ending Cash | B19: ='09_Cash_Flow'!B8 -> -682044816 | C19: ='09_Cash_Flow'!C8 -> 6081922864 | D19: ='09_Cash_Flow'!D8 -> 6863504064 | E19: ='09_Cash_Flow'!E8 -> 11370963904 | F19: ='09_Cash_Flow'!F8 -> 23900064624
